adafruit_si4713.py
adafruit_circuitpython_si4713-1.3.19.dist-info/licenses/LICENSE
adafruit_circuitpython_si4713-1.3.19.dist-info/METADATA
adafruit_circuitpython_si4713-1.3.19.dist-info/WHEEL
adafruit_circuitpython_si4713-1.3.19.dist-info/top_level.txt
adafruit_circuitpython_si4713-1.3.19.dist-info/RECORD
